co/__init__.py
co/cohere.py
co/constants.py
co/entrypoint.py
co/prompt.py
co/utils.py
co_bash-0.0.1.dist-info/LICENSE
co_bash-0.0.1.dist-info/METADATA
co_bash-0.0.1.dist-info/WHEEL
co_bash-0.0.1.dist-info/entry_points.txt
co_bash-0.0.1.dist-info/top_level.txt
co_bash-0.0.1.dist-info/RECORD
