Metadata-Version: 2.1
Name: co-bash
Version: 0.0.1
Summary: UNKNOWN
Home-page: https://github.com/alexOarga/co-bash
Author: Alex Oarga
Author-email: alex718123@gmail.com
License: Apache-2.0 license
Platform: UNKNOWN
Classifier: Programming Language :: Python :: 3
Classifier: Operating System :: OS Independent
Requires-Dist: cohere
Requires-Dist: setuptools
